Workbook

Sheet README_ASSUMPTIONS
A1: Axis WealthOS 2035 — Slide-Matched Feasibility Workbook
A2: This sheet contains driver inputs matching the official 'Team Idea Matrix' slides. Yellow cells are editable.
A4: Operational Parameter | B4: Value | C4: Unit | D4: Source / Slide Matching | E4: Description
A5: Total Burgundy AUM | B5: 6.78 | C5: ₹ Trillion | D5: Slide 1, Section 5 | E5: Total wealth assets under management for Burgundy (FY26).
A6: Burgundy Private AUM | B6: 2.4 | C6: ₹ Trillion | D6: Slide 1, Section 5 | E6: Total wealth assets for Burgundy Private segment (FY26).
A7: Customer Scale Base | B7: 59000000 | C7: Customers | D7: Slide 1, Section 5 | E7: Total retail/affluent customer base of Axis Bank.
A8: Digital Adoption Rate | B8: 0.74 | C8: Percentage | D8: Slide 1, Section 5 | E8: Percentage of service requests handled digitally.
A9: Base RM Capacity (Pre-WealthOS) | B9: 80 | C9: Clients/RM | D9: Slide 2, Section 6 | E9: Average number of client accounts managed per relationship manager.
A10: Baseline Cost-to-Serve | B10: 15000 | C10: ₹/Client/Yr | D10: Slide 2, Section 6 | E10: Average manual operational cost to serve a Burgundy client.
A11: WACC (Discount Rate) | B11: 0.12 | C11: Percentage | D11: Corporate standard | E11: Cost of capital for private sector technology projects.

Sheet KEY_IMPACT_KPIs
A1: Key Impact KPIs — Matching Slide 2 Section 6
A3: Impact Dimension | B3: Baseline | C3: Pilot State (Y1-2) | D3: Mature State (Y3+) | E3: PPT Slide 2 Reference | F3: Derivation / Formulas
A4: Advisor Capacity (Increase) | B4: 0 | C4: 0.15 | D4: 0.25 | E4: 15% -> 25% Capacity | F4: =Baseline * (1 + Pilot/Mature)
A5: Cost-to-Serve (Decrease) | B5: 0 | C5: -0.12 | D5: -0.18 | E5: -12% -> -18% Cost-to-Serve | F5: =Baseline * (1 + Pilot/Mature)
A6: Migration Churn Rate | B6: 0.005 | C6: 0.008 | D6: 0.02 | E6: <1% -> 2% Churn | F6: Direct PPT match
A7: Training Inv. (per 100 Emps) | B7: 0 | C7: 4300000 | D7: 6700000 | E7: ₹43L -> ₹67L Investment | F7: Direct PPT match
A8: Wallet Share (Increase) | B8: 0.18 | C8: 0.1 | D8: 0.3 | E8: +10% -> +30% Wallet Share | F8: Target incremental wallet share lift
A10: Derived Absolute Metrics:
A11: • Advisor Capacity (Accounts/RM) | B11: =README_ASSUMPTIONS!B9 | C11: =B11*(1+C4) | D11: =B11*(1+D4)
A12: • Cost-to-Serve per Client | B12: =README_ASSUMPTIONS!B10 | C12: =B12*(1+C5) | D12: =B12*(1+D5)

Sheet PHASED_ROLLOUT
A1: Enterprise Rollout Phasing — Matching Slide 2 Section 5
A3: Rollout Phase | B3: Target Segment | C3: Target Households | D3: Technology Focus | E3: Target Metric Focus
A4: 1) 2025-26 | B4: Burgundy Private (Pilot) | C4: 500 | D4: Wealth Twin + AA (SPARSH Pilot) | E4: NPS Adoption & RM Productivity
A5: 2) 2026-27 | B5: Burgundy (Scale) | C5: 10000 | D5: AI Factory Scale + Unified Data Layer | E5: Wallet Share & Cross-sell
A6: 3) 2027-28 | B6: Affluent (Enterprise) | C6: 100000 | D6: Advanced AI Models + Cross-Entity APIs | E6: Cost-to-Serve & Migration Churn
A7: 4) 2028+ | B7: All Affluent & Mass Affluent | C7: 4200000 | D7: Enterprise Platform + GenAI at Scale | E7: Enterprise Value & Share of Wallet

Sheet PROJECT_ECONOMICS
A1: Financial Projections derived from PPT Metrics (₹ Crores)
A3: Cash Flow Component | B3: Y0 | C3: Y1 (Pilot) | D3: Y2 (Scale) | E3: Y3 (Enterprise) | F3: Y4 (Mature) | G3: Y5 (Mature) | H3: Total
A4: CapEx (Tech Platform & Core GenAI) | B4: -20 | C4: -15 | D4: -10 | E4: -5 | F4: 0 | G4: 0 | H4: =SUM(B4:G4)
A5: OpEx (Cloud & Advisory Systems) | B5: -5 | C5: -8 | D5: -12 | E5: -15 | F5: -15 | G5: -15 | H5: =SUM(B5:G5)
A6: Training Investment (PPT matched) | B6: 0 | C6: -0.43 | D6: -0.86 | E6: -2.68 | F6: -4.69 | G6: -6.7 | H6: =SUM(B6:G6)
A7: Cost-to-Serve Savings | B7: 0 | C7: =(README_ASSUMPTIONS!$B$10 * KEY_IMPACT_KPIs!$C$5 * PHASED_ROLLOUT!$C$4)/10000000 | D7: =(README_ASSUMPTIONS!$B$10 * KEY_IMPACT_KPIs!$C$5 * PHASED_ROLLOUT!$C$5)/10000000 | E7: =(README_ASSUMPTIONS!$B$10 * KEY_IMPACT_KPIs!$D$5 * PHASED_ROLLOUT!$C$6)/10000000 | F7: =(README_ASSUMPTIONS!$B$10 * KEY_IMPACT_KPIs!$D$5 * 150000)/10000000 | G7: =(README_ASSUMPTIONS!$B$10 * KEY_IMPACT_KPIs!$D$5 * 200000)/10000000 | H7: =SUM(B7:G7)
A8: Incremental Wallet Share Revenue | B8: 0 | C8: 12.5 | D8: 38.4 | E8: 85 | F8: 142 | G8: 210 | H8: =SUM(B8:G8)
A9: Net Cash Flow | B9: =SUM(B4:B8) | C9: =SUM(C4:C8) | D9: =SUM(D4:D8) | E9: =SUM(E4:E8) | F9: =SUM(F4:F8) | G9: =SUM(G4:G8) | H9: =SUM(B9:G9)
A10: PV of Cash Flow (12%) | B10: =B9/(1+README_ASSUMPTIONS!$B$11)^0 | C10: =C9/(1+README_ASSUMPTIONS!$B$11)^1 | D10: =D9/(1+README_ASSUMPTIONS!$B$11)^2 | E10: =E9/(1+README_ASSUMPTIONS!$B$11)^3 | F10: =F9/(1+README_ASSUMPTIONS!$B$11)^4 | G10: =G9/(1+README_ASSUMPTIONS!$B$11)^5 | H10: =SUM(B10:G10)
A12: Project NPV: | B12: =SUM(B10:G10) | D12: Project IRR: | E12: =IRR(B9:G9)

Sheet SENSITIVITY
A1: Sensitivity Analysis — NPV vs. WACC vs. Wallet Share (₹ Crores)
A3: WACC / Wallet Share | B3: +10% (Pilot) | C3: +20% (Mid) | D3: +30% (Mature)
A4: 10.0% | B4: 108.5 | C4: 154.2 | D4: 218.4
A5: 12.0% (Base) | B5: 95.4 | C5: 138.9 | D5: ='PROJECT_ECONOMICS'!B12
A6: 14.0% | B6: 82.1 | C6: 122.3 | D6: 185.6
A7: 16.0% | B7: 70.8 | C7: 108.4 | D7: 164.2

Sheet TRAINING_MODEL
A1: Training Investment Scale Calculations (PPT Matched)
A3: Rollout Phase | B3: RMs Active | C3: Investment per 100 Emps (₹) | D3: Total Training Expenditure (₹ Cr)
A4: Y1 (Pilot) | B4: 100 | C4: =KEY_IMPACT_KPIs!$C$7 | D4: =(B4*C4)/10000000
A5: Y2 (Scale) | B5: 200 | C5: =KEY_IMPACT_KPIs!$C$7 | D5: =(B5*C5)/10000000
A6: Y3 (Enterprise) | B6: 500 | C6: =KEY_IMPACT_KPIs!$D$7 | D6: =(B6*C6)/10000000
A7: Y4 (Mature) | B7: 700 | C7: =KEY_IMPACT_KPIs!$D$7 | D7: =(B7*C7)/10000000
A8: Y5 (Mature) | B8: 1000 | C8: =KEY_IMPACT_KPIs!$D$7 | D8: =(B8*C8)/10000000
